{
    "title": "My Projects",
    "projects": [
        {
            "name": "PentaCal",
            "tech": [
                "PHP",
                "Custom Web Components",
                "Pub/Sub State",
                "JavaScript",
                "JSON Database"
            ],
            "description": {
                "problem": "People often struggle to coordinate events, communicate and stay updated within their social circles in one unified place.",
                "solution": "Built a prototype that combines messaging and calendar‑based group coordination. The backend uses a PHP API with a JSON data layer, while the frontend is implemented in vanilla JavaScript with custom components, view‑specific modules, a lightweight routing approach and a pub/sub‑driven state system. The project focuses on architecture, modularity and team‑based full‑stack development rather than a finished product."
            }
        },
        {
            "name": "ShelfWise",
            "tech": [
                "TypeScript",
                "SQLite",
                "JWT",
                "Deno"
            ],
            "description": {
                "problem": "Teams needed a secure and structured way to manage inventory with proper authentication, role control and reliable data handling.",
                "solution": "A full‑stack inventory system with JWT auth, RBAC, modular Deno backend, structured logging. Focus on clarity, maintainability and DevOps‑oriented architecture."
            }
        },
        {
            "name": "PackIT",
            "tech": [
                "Deno",
                "Cookies",
                "REST APIs",
                "JavaScript",
                "SPA Navigation"
            ],
            "description": {
                "problem": "Travelers needed a way to create, save and manage packing lists across multiple trips with persistent user data.",
                "solution": "Built an agile full‑stack service with authentication via cookies, internal/external API integration, automated tests and SPA navigation. Contributed to both backend structure and frontend architecture."
            }
        },
        {
            "name": "City Management Web Service",
            "tech": [
                "Deno",
                "CORS",
                "Fetch API",
                "DOM",
                "Validation"
            ],
            "description": {
                "problem": "Users needed a simple interface to manage, search and validate city data with real‑time feedback.",
                "solution": "Created a CRUD web service with dynamic UI updates, search functionality, in‑browser API testing, consistent error handling and a modular codebase separating frontend logic, tests and server API."
            }
        }
    ]
}